mainnet/__init__.py
mainnet/api_client.py
mainnet/configuration.py
mainnet/exceptions.py
mainnet/rest.py
mainnet/api/__init__.py
mainnet/api/contract_api.py
mainnet/api/contract_escrow_api.py
mainnet/api/faucet_api.py
mainnet/api/mine_api.py
mainnet/api/util_api.py
mainnet/api/wallet_api.py
mainnet/api/wallet_bcmr_api.py
mainnet/api/wallet_signed_api.py
mainnet/api/wallet_util_api.py
mainnet/api/webhook_api.py
mainnet/models/__init__.py
mainnet/models/auth_chain_element.py
mainnet/models/balance_request.py
mainnet/models/balance_response.py
mainnet/models/cashscript_receipt.py
mainnet/models/contract.py
mainnet/models/contract_fn_request.py
mainnet/models/contract_fn_response.py
mainnet/models/contract_info_request.py
mainnet/models/contract_info_response.py
mainnet/models/contract_request.py
mainnet/models/contract_response.py
mainnet/models/convert_request.py
mainnet/models/create_signed_message_request.py
mainnet/models/deposit_address_response.py
mainnet/models/electrum_raw_transaction.py
mainnet/models/electrum_raw_transaction_script_pub_key.py
mainnet/models/electrum_raw_transaction_script_sig.py
mainnet/models/electrum_raw_transaction_vin.py
mainnet/models/electrum_raw_transaction_vout.py
mainnet/models/encode_transaction_request.py
mainnet/models/encode_transaction_response.py
mainnet/models/error.py
mainnet/models/escrow_contract.py
mainnet/models/escrow_fn_request.py
mainnet/models/escrow_info_request.py
mainnet/models/escrow_info_response.py
mainnet/models/escrow_request.py
mainnet/models/escrow_response.py
mainnet/models/get_addresses_response.py
mainnet/models/get_addrs_by_xpub_key_request.py
mainnet/models/get_testnet_bch_request.py
mainnet/models/get_testnet_bch_response.py
mainnet/models/get_xpub_key_info_request.py
mainnet/models/get_xpub_key_info_response.py
mainnet/models/history_request.py
mainnet/models/history_response.py
mainnet/models/inline_object.py
mainnet/models/inline_object1.py
mainnet/models/inline_object2.py
mainnet-2.3.11.dist-info/METADATA
mainnet-2.3.11.dist-info/WHEEL
mainnet-2.3.11.dist-info/top_level.txt
mainnet-2.3.11.dist-info/RECORD
