Metadata-Version: 2.1
Name: mainnet
Version: 2.3.11
Summary: Mainnet Cash
Home-page: 
Author: OpenAPI Generator community
Author-email: hello@mainnet.cash
License: MIT Licence
Keywords: OpenAPI,OpenAPI-Generator,Mainnet Cash
Requires-Dist: urllib3 >=1.15
Requires-Dist: six >=1.10
Requires-Dist: certifi
Requires-Dist: python-dateutil
